<corpus lang="english"><lexelt item="receive.v" pos="unk"><instance docscr="SEMCORE" id="receive.v.0"><context><head>receive</head> the exchange.
</context></instance><instance docscr="SEMCORE" id="receive.v.1"><context><head>receive</head> the money.
</context></instance><instance docscr="SEMCORE" id="receive.v.2"><context><head>receive</head> the portion.
</context></instance><instance docscr="SEMCORE" id="receive.v.3"><context><head>receive</head> the vote.
</context></instance><instance docscr="SEMCORE" id="receive.v.4"><context><head>receive</head> the telephone_call.
</context></instance><instance docscr="SEMCORE" id="receive.v.5"><context><head>receive</head> the call.
</context></instance><instance docscr="SEMCORE" id="receive.v.6"><context><head>receive</head> the payment.
</context></instance><instance docscr="SEMCORE" id="receive.v.7"><context><head>receive</head> the payment.
</context></instance><instance docscr="SEMCORE" id="receive.v.8"><context><head>receive</head> the one-half.
</context></instance><instance docscr="SEMCORE" id="receive.v.9"><context><head>receive</head> the questionnaire.
</context></instance><instance docscr="SEMCORE" id="receive.v.10"><context><head>receive</head> the resume.
</context></instance><instance docscr="SEMCORE" id="receive.v.11"><context><head>receive</head> the contract.
</context></instance><instance docscr="SEMCORE" id="receive.v.12"><context><head>receive</head> the copy.
</context></instance><instance docscr="SEMCORE" id="receive.v.13"><context><head>receive</head> the award.
</context></instance><instance docscr="SEMCORE" id="receive.v.14"><context><head>receive</head> the attention.
</context></instance><instance docscr="SEMCORE" id="receive.v.15"><context><head>receive</head> the honor.
</context></instance><instance docscr="SEMCORE" id="receive.v.16"><context><head>receive</head> the drug.
</context></instance><instance docscr="SEMCORE" id="receive.v.17"><context><head>receive</head> the notice.
</context></instance><instance docscr="SEMCORE" id="receive.v.18"><context><head>receive</head> the price.
</context></instance><instance docscr="SEMCORE" id="receive.v.19"><context><head>receive</head> the wage.
</context></instance><instance docscr="SEMCORE" id="receive.v.20"><context><head>receive</head> the salary.
</context></instance><instance docscr="SEMCORE" id="receive.v.21"><context><head>receive</head> the flux.
</context></instance><instance docscr="SEMCORE" id="receive.v.22"><context><head>receive</head> the medicine.
</context></instance><instance docscr="SEMCORE" id="receive.v.23"><context><head>receive</head> the money.
</context></instance><instance docscr="SEMCORE" id="receive.v.24"><context><head>receive</head> the hundred.
</context></instance><instance docscr="SEMCORE" id="receive.v.25"><context><head>receive</head> the prize.
</context></instance><instance docscr="SEMCORE" id="receive.v.26"><context><head>receive</head> the variety.
</context></instance><instance docscr="SEMCORE" id="receive.v.27"><context><head>receive</head> the meal.
</context></instance><instance docscr="SEMCORE" id="receive.v.28"><context><head>receive</head> the diet.
</context></instance><instance docscr="SEMCORE" id="receive.v.29"><context><head>receive</head> the report.
</context></instance><instance docscr="SEMCORE" id="receive.v.30"><context><head>receive</head> the remuneration.
</context></instance><instance docscr="SEMCORE" id="receive.v.31"><context><head>receive</head> the telephone_call.
</context></instance><instance docscr="SEMCORE" id="receive.v.32"><context><head>receive</head> the check.
</context></instance></lexelt><lexelt item="award.n" pos="unk"><instance docscr="SEMCORE" id="award.n.0"><context>receive the <head>award</head>.
</context></instance></lexelt><lexelt item="vote.n" pos="unk"><instance docscr="SEMCORE" id="vote.n.0"><context>receive the <head>vote</head>.
</context></instance></lexelt><lexelt item="payment.n" pos="unk"><instance docscr="SEMCORE" id="payment.n.0"><context>receive the <head>payment</head>.
</context></instance><instance docscr="SEMCORE" id="payment.n.1"><context>receive the <head>payment</head>.
</context></instance></lexelt><lexelt item="variety.n" pos="unk"><instance docscr="SEMCORE" id="variety.n.0"><context>receive the <head>variety</head>.
</context></instance></lexelt><lexelt item="one-half.n" pos="unk"><instance docscr="SEMCORE" id="one-half.n.0"><context>receive the <head>one-half</head>.
</context></instance></lexelt><lexelt item="questionnaire.n" pos="unk"><instance docscr="SEMCORE" id="questionnaire.n.0"><context>receive the <head>questionnaire</head>.
</context></instance></lexelt><lexelt item="resume.n" pos="unk"><instance docscr="SEMCORE" id="resume.n.0"><context>receive the <head>resume</head>.
</context></instance></lexelt><lexelt item="meal.n" pos="unk"><instance docscr="SEMCORE" id="meal.n.0"><context>receive the <head>meal</head>.
</context></instance></lexelt><lexelt item="hundred.n" pos="unk"><instance docscr="SEMCORE" id="hundred.n.0"><context>receive the <head>hundred</head>.
</context></instance></lexelt><lexelt item="exchange.n" pos="unk"><instance docscr="SEMCORE" id="exchange.n.0"><context>receive the <head>exchange</head>.
</context></instance></lexelt><lexelt item="wage.n" pos="unk"><instance docscr="SEMCORE" id="wage.n.0"><context>receive the <head>wage</head>.
</context></instance></lexelt><lexelt item="contract.n" pos="unk"><instance docscr="SEMCORE" id="contract.n.0"><context>receive the <head>contract</head>.
</context></instance></lexelt><lexelt item="salary.n" pos="unk"><instance docscr="SEMCORE" id="salary.n.0"><context>receive the <head>salary</head>.
</context></instance></lexelt><lexelt item="portion.n" pos="unk"><instance docscr="SEMCORE" id="portion.n.0"><context>receive the <head>portion</head>.
</context></instance></lexelt><lexelt item="diet.n" pos="unk"><instance docscr="SEMCORE" id="diet.n.0"><context>receive the <head>diet</head>.
</context></instance></lexelt><lexelt item="flux.n" pos="unk"><instance docscr="SEMCORE" id="flux.n.0"><context>receive the <head>flux</head>.
</context></instance></lexelt><lexelt item="notice.n" pos="unk"><instance docscr="SEMCORE" id="notice.n.0"><context>receive the <head>notice</head>.
</context></instance></lexelt><lexelt item="price.n" pos="unk"><instance docscr="SEMCORE" id="price.n.0"><context>receive the <head>price</head>.
</context></instance></lexelt><lexelt item="prize.n" pos="unk"><instance docscr="SEMCORE" id="prize.n.0"><context>receive the <head>prize</head>.
</context></instance></lexelt><lexelt item="telephone_call.n" pos="unk"><instance docscr="SEMCORE" id="telephone_call.n.0"><context>receive the <head>telephone_call</head>.
</context></instance><instance docscr="SEMCORE" id="telephone_call.n.1"><context>receive the <head>telephone_call</head>.
</context></instance></lexelt><lexelt item="remuneration.n" pos="unk"><instance docscr="SEMCORE" id="remuneration.n.0"><context>receive the <head>remuneration</head>.
</context></instance></lexelt><lexelt item="call.n" pos="unk"><instance docscr="SEMCORE" id="call.n.0"><context>receive the <head>call</head>.
</context></instance></lexelt><lexelt item="drug.n" pos="unk"><instance docscr="SEMCORE" id="drug.n.0"><context>receive the <head>drug</head>.
</context></instance></lexelt><lexelt item="check.n" pos="unk"><instance docscr="SEMCORE" id="check.n.0"><context>receive the <head>check</head>.
</context></instance></lexelt><lexelt item="attention.n" pos="unk"><instance docscr="SEMCORE" id="attention.n.0"><context>receive the <head>attention</head>.
</context></instance></lexelt><lexelt item="medicine.n" pos="unk"><instance docscr="SEMCORE" id="medicine.n.0"><context>receive the <head>medicine</head>.
</context></instance></lexelt><lexelt item="honor.n" pos="unk"><instance docscr="SEMCORE" id="honor.n.0"><context>receive the <head>honor</head>.
</context></instance></lexelt><lexelt item="copy.n" pos="unk"><instance docscr="SEMCORE" id="copy.n.0"><context>receive the <head>copy</head>.
</context></instance></lexelt><lexelt item="money.n" pos="unk"><instance docscr="SEMCORE" id="money.n.0"><context>receive the <head>money</head>.
</context></instance><instance docscr="SEMCORE" id="money.n.1"><context>receive the <head>money</head>.
</context></instance></lexelt><lexelt item="report.n" pos="unk"><instance docscr="SEMCORE" id="report.n.0"><context>receive the <head>report</head>.
</context></instance></lexelt></corpus>